README.md
setup.py
ctec_pytest_utils/__init__.py
ctec_pytest_utils/pytest_utils.py
ctec_pytest_utils.egg-info/PKG-INFO
ctec_pytest_utils.egg-info/SOURCES.txt
ctec_pytest_utils.egg-info/dependency_links.txt
ctec_pytest_utils.egg-info/requires.txt
ctec_pytest_utils.egg-info/top_level.txt