Metadata-Version: 1.1
Name: ctec-pytest-utils
Version: 0.0.3
Summary: 189 pytest utils
Home-page: http://www.189.cn
Author: jjy
Author-email: rxxy0101@163.com
License: UNKNOWN
Platform: UNKNOWN
Classifier: Programming Language :: Python :: 2
Classifier: Programming Language :: Python :: 2.6
Classifier: Programming Language :: Python :: 2.7
Classifier: Programming Language :: Python :: 3
